[
  {
    "STT": 1,
    "Anh": "",
    "Ho_va_Ten": "Trần Xuân May",
    "Ngay_sinh": "02.09.65",
    "Ngay_vao_Dang": "05.12.1999",
    "So_the_Dang": "92023398 042829",
    "Chuc_vu": "Lái xe",
    "Trinh_do": "10/10 - Lái xe",
    "Que_quan": "Việt Hoà - Khoái Châu - Hưng Yên",
    "Chuc_vu_Dang": ""
  },
  {
    "STT": 2,
    "Anh": "",
    "Ho_va_Ten": "Nguyễn Đình Được",
    "Ngay_sinh": "24.10.1982",
    "Ngay_vao_Dang": "28.02.2013",
    "So_the_Dang": "83022797 045501",
    "Chuc_vu": "Lái xe",
    "Trinh_do": "12/12 - LĐPT",
    "Que_quan": "Mai Đình - Sóc Sơn - Hà Nội",
    "Chuc_vu_Dang": ""
  },
  {
    "STT": 3,
    "Anh": "",
    "Ho_va_Ten": "Nguyễn Duy Hoan",
    "Ngay_sinh": "26.06.70",
    "Ngay_vao_Dang": "19.05.2001",
    "So_the_Dang": "92002414 042966",
    "Chuc_vu": "Đội trưởng",
    "Trinh_do": "12/12 - CN Kinh tế",
    "Que_quan": "Trang Bảo Xá - Quỳnh Phụ - Thái Bình",
    "Chuc_vu_Dang": "Bí thư CB"
  },
  {
    "STT": 4,
    "Anh": "",
    "Ho_va_Ten": "Ngô Thế Giang",
    "Ngay_sinh": "05.7.1976",
    "Ngay_vao_Dang": "10.7.2018",
    "So_the_Dang": "83044317",
    "Chuc_vu": "",
    "Trinh_do": "12/12 - Lái xe",
    "Que_quan": "X. Nga Bạch - H. Nga Sơn - T. Thanh Hoá",
    "Chuc_vu_Dang": ""
  },
  {
    "STT": 5,
    "Anh": "",
    "Ho_va_Ten": "Hoàng Trung Kiên",
    "Ngay_sinh": "11.10.1984",
    "Ngay_vao_Dang": "09.12.2016",
    "So_the_Dang": "83039530 022604",
    "Chuc_vu": "Tổ phó",
    "Trinh_do": "12/12",
    "Que_quan": "Thành Lợi- Vụ Bản- Nam Định",
    "Chuc_vu_Dang": "CUV"
  },
  {
    "STT": 6,
    "Anh": "",
    "Ho_va_Ten": "Hoàng Văn Thành",
    "Ngay_sinh": "20.10.1992",
    "Ngay_vao_Dang": "11.7.2019",
    "So_the_Dang": "83047818",
    "Chuc_vu": "Nhân viên",
    "Trinh_do": "12/12 - Cử nhân Luật kinh tế",
    "Que_quan": "Xã Xuân Trường- Nghi Xuân- Hà Tĩnh",
    "Chuc_vu_Dang": ""
  },
  {
    "STT": 7,
    "Anh": "",
    "Ho_va_Ten": "Phạm Quang Nhàn",
    "Ngay_sinh": "10.12.1983",
    "Ngay_vao_Dang": "02.11.2011",
    "So_the_Dang": "83019930",
    "Chuc_vu": "Nhân viên",
    "Trinh_do": "12/12 - Lái xe",
    "Que_quan": "Thanh Xuân - Sóc Sơn  - Hà Nội",
    "Chuc_vu_Dang": ""
  },
  {
    "STT": 8,
    "Anh": "",
    "Ho_va_Ten": "Phạm Tự Cường",
    "Ngay_sinh": "29.08.65",
    "Ngay_vao_Dang": "29.11.2006",
    "So_the_Dang": "92034751 044185",
    "Chuc_vu": "Phó đội trưởng",
    "Trinh_do": "10/10 - Trung cấp Xây dựng",
    "Que_quan": "Giao Tiến - Giao Thuỷ - Nam Định",
    "Chuc_vu_Dang": "Phó BTCB"
  },
  {
    "STT": 9,
    "Anh": "",
    "Ho_va_Ten": "Trần Anh Tuyên",
    "Ngay_sinh": "23.12.1982",
    "Ngay_vao_Dang": "",
    "So_the_Dang": "",
    "Chuc_vu": "Nhân viên",
    "Trinh_do": "12/12 - Lái xe",
    "Que_quan": "X. Hồng Khê, H. Bình Giang, T. Hải Dương.",
    "Chuc_vu_Dang": "ĐVDB"
  },
  {
    "STT": 10,
    "Anh": "",
    "Ho_va_Ten": "Nguyễn Việt Nam",
    "Ngay_sinh": "12.12.1993",
    "Ngay_vao_Dang": "",
    "So_the_Dang": "",
    "Chuc_vu": "Nhân viên",
    "Trinh_do": "12/12 - Lái xe",
    "Que_quan": "P. Hòa Long, TP. Bắc Ninh, T. Bắc Ninh",
    "Chuc_vu_Dang": "ĐVDB"
  }
]